llm_ripper/__init__.py
llm_ripper/cli.py
llm_ripper/py.typed
llm_ripper/__pycache__/__init__.cpython-313.pyc
llm_ripper/__pycache__/cli.cpython-313.pyc
llm_ripper/bridge/__init__.py
llm_ripper/bridge/align.py
llm_ripper/bridge/__pycache__/__init__.cpython-313.pyc
llm_ripper/bridge/__pycache__/align.cpython-313.pyc
llm_ripper/causal/__init__.py
llm_ripper/causal/tracer.py
llm_ripper/causal/__pycache__/__init__.cpython-313.pyc
llm_ripper/causal/__pycache__/tracer.cpython-313.pyc
llm_ripper/core/__init__.py
llm_ripper/core/activation_capture.py
llm_ripper/core/analysis.py
llm_ripper/core/extraction.py
llm_ripper/core/transplant.py
llm_ripper/core/validation.py
llm_ripper/core/__pycache__/__init__.cpython-313.pyc
llm_ripper/core/__pycache__/extraction.cpython-313.pyc
llm_ripper/counterfactual/__init__.py
llm_ripper/counterfactual/evaluator.py
llm_ripper/counterfactual/generator.py
llm_ripper/counterfactual/__pycache__/__init__.cpython-313.pyc
llm_ripper/counterfactual/__pycache__/evaluator.cpython-313.pyc
llm_ripper/counterfactual/__pycache__/generator.cpython-313.pyc
llm_ripper/features/__init__.py
llm_ripper/features/sae.py
llm_ripper/features/__pycache__/__init__.cpython-313.pyc
llm_ripper/features/__pycache__/sae.cpython-313.pyc
llm_ripper/interop/__init__.py
llm_ripper/interop/adapters.py
llm_ripper/interop/merge.py
llm_ripper/interop/tokenize_align.py
llm_ripper/interop/__pycache__/__init__.cpython-313.pyc
llm_ripper/interop/__pycache__/adapters.cpython-313.pyc
llm_ripper/interop/__pycache__/merge.cpython-313.pyc
llm_ripper/interop/__pycache__/tokenize_align.cpython-313.pyc
llm_ripper/safety/__init__.py
llm_ripper/safety/provenance.py
llm_ripper/safety/report.py
llm_ripper/safety/stress.py
llm_ripper/safety/__pycache__/__init__.cpython-313.pyc
llm_ripper/safety/__pycache__/provenance.cpython-313.pyc
llm_ripper/safety/__pycache__/report.cpython-313.pyc
llm_ripper/safety/__pycache__/stress.cpython-313.pyc
llm_ripper/studio/__init__.py
llm_ripper/studio/server.py
llm_ripper-1.0.0.dist-info/licenses/LICENSE
llm_ripper-1.0.0.dist-info/licenses/NOTICE
llm_ripper-1.0.0.dist-info/METADATA
llm_ripper-1.0.0.dist-info/WHEEL
llm_ripper-1.0.0.dist-info/entry_points.txt
llm_ripper-1.0.0.dist-info/top_level.txt
llm_ripper-1.0.0.dist-info/RECORD
