Metadata-Version: 2.4
Name: llm-ripper
Version: 1.0.0
Summary: A production framework for modular deconstruction, analysis, and recomposition of knowledge in Transformer-based language models
Author-email: qrv0 <qorvuscompany@gmail.com>
License: Apache-2.0
Project-URL: Homepage, https://github.com/qrv0/LLM-Ripper
Project-URL: Repository, https://github.com/qrv0/LLM-Ripper
Classifier: Development Status :: 5 - Production/Stable
Classifier: Intended Audience :: Developers
Classifier: Intended Audience :: Science/Research
Classifier: License :: OSI Approved :: Apache Software License
Classifier: Operating System :: OS Independent
Classifier: Programming Language :: Python :: 3
Classifier: Programming Language :: Python :: 3.8
Classifier: Programming Language :: Python :: 3.9
Classifier: Programming Language :: Python :: 3.10
Classifier: Programming Language :: Python :: 3.11
Classifier: Topic :: Scientific/Engineering :: Artificial Intelligence
Classifier: Topic :: Software Development :: Libraries :: Python Modules
Requires-Python: >=3.8
License-File: LICENSE
License-File: NOTICE
Requires-Dist: torch>=2.0.0
Requires-Dist: transformers<5,>=4.30.0
Requires-Dist: safetensors>=0.3.0
Requires-Dist: h5py>=3.8.0
Requires-Dist: numpy>=1.24.0
Requires-Dist: scikit-learn>=1.3.0
Requires-Dist: numba>=0.60.0; python_version >= "3.11"
Requires-Dist: llvmlite>=0.43.0; python_version >= "3.11"
Requires-Dist: tqdm>=4.65.0
Requires-Dist: datasets>=2.12.0
Requires-Dist: accelerate>=0.20.0
Requires-Dist: tokenizers>=0.13.0
Requires-Dist: scipy>=1.10.0
Requires-Dist: pandas>=2.0.0
Requires-Dist: python-dotenv>=1.0.1
Requires-Dist: PyYAML>=6.0
Provides-Extra: viz
Requires-Dist: matplotlib>=3.7.0; extra == "viz"
Requires-Dist: seaborn>=0.12.0; extra == "viz"
Requires-Dist: umap-learn>=0.5.6; extra == "viz"
Provides-Extra: spacy
Requires-Dist: spacy>=3.6.0; extra == "spacy"
Provides-Extra: wandb
Requires-Dist: wandb>=0.15.0; extra == "wandb"
Provides-Extra: nlp
Requires-Dist: nltk>=3.8.0; extra == "nlp"
Dynamic: license-file
